README.md
setup.py
pewpew/__init__.py
pewpew/_context.py
pewpew/_context_test.py
pewpew/_decorator.py
pewpew/_logging.py
pewpew/_plotting.py
pewpew/api.py
pewpew/beam.py
pewpew/beam_test.py
pewpew/tracing.py
pewpew/tracing_test.py
pewpew.egg-info/PKG-INFO
pewpew.egg-info/SOURCES.txt
pewpew.egg-info/dependency_links.txt
pewpew.egg-info/requires.txt
pewpew.egg-info/top_level.txt
pewpew/utils/__init__.py
pewpew/utils/iterables.py
pewpew/utils/iterables_test.py
pewpew/utils/patching.py
pewpew/utils/validation.py
pewpew/utils/validation_test.py